{"data":{"tag":{"title":"Docker","belongsTo":{"totalCount":2,"pageInfo":{"totalPages":1,"currentPage":1},"edges":[{"node":{"title":"Docker pour les développeurs: Environment as Code","timeToRead":4,"date":"August 2, 2015","path":"/blog/2015-08-02-docker-pour-les-developpeurs-environment-as-code","summary":"Utiliser Docker comme un environnement de développement complet.","tags":[{"title":"Docker"},{"title":"Docker-Compose"},{"title":"DevOps"},{"title":"GiantSwarm"},{"title":"Rancher"}]}},{"node":{"title":"Utiliser Docker derriere un proxy sur CoreOS","timeToRead":1,"date":"July 5, 2015","path":"/blog/2015-07-05-utiliser-docker-derriere-un-proxy-sur-core-os","summary":"Petit tips du jour qui pourra sauver l'après midi de certains...","tags":[{"title":"Docker"},{"title":"CoreOS"},{"title":"proxy"},{"title":"DevOps"}]}}]}}},"context":{}}